flask_redis.py
Flask_And_Redis-1.0.0.dist-info/AUTHORS.rst
Flask_And_Redis-1.0.0.dist-info/LICENSE
Flask_And_Redis-1.0.0.dist-info/METADATA
Flask_And_Redis-1.0.0.dist-info/WHEEL
Flask_And_Redis-1.0.0.dist-info/top_level.txt
Flask_And_Redis-1.0.0.dist-info/RECORD
