Metadata-Version: 2.1
Name: Flask-And-Redis
Version: 1.0.0
Summary: Simple as dead support of Redis database for Flask apps.
Home-page: https://github.com/playpauseandstop/Flask-And-Redis
Author: Igor Davydenko
Author-email: playpauseandstop@gmail.com
License: BSD License
Keywords: flask redis
Platform: any
Classifier: Development Status :: 5 - Production/Stable
Classifier: Environment :: Web Environment
Classifier: Operating System :: OS Independent
Classifier: Topic :: Utilities
Classifier: Programming Language :: Python :: 2
Classifier: Programming Language :: Python :: 2.7
Classifier: Programming Language :: Python :: 3
Classifier: Programming Language :: Python :: 3.4
Classifier: Programming Language :: Python :: 3.5
Classifier: Programming Language :: Python :: 3.6
Classifier: Programming Language :: Python :: 3.7
Classifier: Programming Language :: Python :: Implementation :: PyPy
Classifier: Topic :: Internet :: WWW/HTTP :: Dynamic Content
Classifier: Topic :: Software Development :: Libraries :: Python Modules
Classifier: License :: OSI Approved :: BSD License
Requires-Dist: Flask (>=0.8)
Requires-Dist: redis (>=2.4.11)
